{"results": [{"input": ["it", "'s", "okay", "."], "pred": [["i", "don", "'t", "know", "why"], ["i", "don", "'t", "think", "so"], ["come", "on", "let", "'s", "go"], ["i", ".", "l", "be", "right", "back"], ["what", "do", "you", "mean", "?"], ["what", "'s", "the", "matter", "?"], ["don", "'t", "worry", "about", "it"], ["what", "are", "you", "doing", "?"], ["you", "can", "'t", "do", "that"], ["i", "can", "'t", "believe", "it"]], "scores": [-8.59394645690918, -6.893839061260223, -8.28798919916153, -7.919674336910248, -6.7155433893203735, -6.633763313293457, -7.451134264469147, -5.847864270210266, -9.044551849365234, -7.065803587436676]}, {"input": ["where", "'s", "ma", "?"], "pred": [["i", "don", "'t", "think", "so"], ["it", "'s", "not", "my", "fault"], ["i", "?", "l", "be", "right", "back"], ["let", "'s", "get", "out", "of", "here"], ["where", "have", "you", "been", "?"], ["i", "?", "l", "take", "care", "of", "it"], ["where", "are", "you", "going", "?"], ["i", "'m", "glad", "you", "'r", "e", "here"], ["what", "'s", "the", "matter", "?"], ["don", "'t", "worry", "about", "it"]], "scores": [-7.532513856887817, -9.368886321783066, -7.246384680271149, -8.505226075649261, -6.899656057357788, -8.837199598550797, -5.499309599399567, -9.262509286403656, -5.608722448348999, -8.312373518943787]}, {"input": ["bravo", ",", "your", "majesty", "!"], "pred": [["i", "!", "l", "be", "right", "back"], ["i", "don", "'t", "think", "so"], ["what", "are", "you", "doing", "?"], ["what", "do", "you", "mean", "?"], ["what", "do", "you", "want", "?"], ["you", "'r", "e", "under", "arrest"], [",", "majesty", "majesty", "majesty", "!"], ["come", "on", "let", "'s", "go", "!"], ["i", "beg", "your", "pardon", "?"], ["get", "out", "of", "here", "!"]], "scores": [-9.41220474243164, -9.189893573522568, -6.586719274520874, -7.185009241104126, -6.925978481769562, -9.621371746063232, -9.545256912708282, -8.796592116355896, -7.850309789180756, -7.650531232357025]}, {"input": ["your", "men", "knew", "the", "risks", "."], "pred": [["i", "don", "'t", "think", "so"], ["you", "'r", "e", "a", "."], ["what", "do", "you", "mean", "?"], ["i", ".", "l", "tell", "you", "what"], ["why", "didn", "'t", "you", "tell", "me", "?"], ["i", ".", "e", "been", "thinking"], ["that", "'s", "not", "the", "point"], ["you", ".", "e", "got", "to", "understand"], ["i", "didn", "'t", "know", "that"], ["how", "do", "you", "know", "?"]], "scores": [-8.359031319618225, -9.96957552433014, -6.662775635719299, -9.508278131484985, -8.940271452069283, -10.099640965461731, -9.515234291553497, -11.37643313407898, -9.753592073917389, -8.227634310722351]}, {"input": ["aren", "'t", "you", "coming", "?"], "pred": [["i", "?", "e", "got", "to", "go"], ["what", "are", "you", "doing", "?"], ["i", "'m", "in", "a", "hurry"], ["i", "?", "l", "be", "right", "back"], ["i", "?", "l", "take", "care", "of", "it"], ["what", "do", "you", "want", "?"], ["i", "don", "'t", "think", "so"], ["what", "'s", "the", "matter", "?"], ["come", "on", "let", "'s", "go"], ["you", "'r", "e", "all", "right"]], "scores": [-8.281749367713928, -4.9677735567092896, -9.011568367481232, -6.8701698780059814, -8.758547350764275, -6.951804518699646, -7.548417747020721, -5.698029518127441, -7.737420558929443, -8.988520622253418]}, {"input": ["where", "the", "hell", "is", "he", "?"], "pred": [["where", "are", "you", "going", "?"], ["he", "?", "l", "be", "all", "right"], ["i", "don", "'t", "think", "so"], ["where", "is", "he", "now", "?"], ["i", "?", "l", "be", "right", "back"], ["what", "'s", "the", "matter", "?"], ["i", "don", "'t", "know", "where", "he", "is"], ["i", "?", "e", "got", "to", "go"], ["i", "?", "e", "seen", "him"], ["i", "don", "'t", "want", "to", "hear", "it"]], "scores": [-6.800319612026215, -9.043801173567772, -7.708199560642242, -6.746421217918396, -7.918190956115723, -6.657063961029053, -8.879709899425507, -10.020329892635345, -9.632686734199524, -11.480572819709778]}, {"input": ["what", "'s", "the", "matter", "?"], "pred": [["i", "?", "l", "be", "right", "back"], ["i", "don", "'t", "think", "so"], ["what", "'s", "the", "matter", "?"], ["what", "are", "you", "doing", "?"], ["what", "the", "hell", "are", "you", "doing", "?"], ["i", "don", "'t", "know", "what", "to", "say"], ["i", "?", "e", "got", "to", "go"], ["what", "are", "you", "going", "to", "do", "?"], ["i", "can", "'t", "believe", "it"], ["come", "on", "let", "'s", "go"]], "scores": [-7.58696049451828, -7.619533061981201, -4.972449541091919, -5.382215261459351, -7.726113677024841, -9.193811774253845, -8.950499057769775, -8.488839119672775, -8.126605749130249, -7.690726310014725]}, {"input": ["you", "'re", "kidding", "."], "pred": [["i", "don", "'t", "think", "so"], ["what", "do", "you", "think", "you", "'r", "e", "doing", "?"], ["what", "do", "you", "mean", "?"], ["i", ".", "l", "be", "right", "back"], ["what", "'s", "the", "matter", "?"], ["you", "know", "what", "i", "mean", "?"], ["what", "are", "you", "talking", "about", "?"], ["i", ".", "e", "been", "thinking"], ["i", "can", "'t", "believe", "it"], ["i", ".", "e", "got", "to", "go"]], "scores": [-7.19914972782135, -9.177346408367157, -6.066099524497986, -8.676567077636719, -7.145774483680725, -8.820784270763397, -6.3201903104782104, -9.695402264595032, -8.050856113433838, -10.628830313682556]}, {"input": ["why", "not", "religion", ",", "dad", "?"], "pred": [["i", "don", "'t", "know", "why"], ["why", "didn", "'t", "you", "tell", "me", "?"], ["what", "do", "you", "mean", "?"], ["i", "don", "'t", "think", "so"], ["i", "?", "e", "been", "thinking"], ["what", "'s", "the", "matter", "?"], ["you", "'r", "e", "a", "?"], ["i", "?", "l", "tell", "you", "why"], ["that", "'s", "why", "i", "'m", "here"], ["that", "'s", "why", "we", "'r", "e", "here"]], "scores": [-8.29572880268097, -8.952090084552765, -6.630517959594727, -7.740748167037964, -10.864499807357788, -8.08430826663971, -10.726045489311218, -10.146181166172028, -9.172610193490982, -9.929959088563919]}, {"input": ["what", "will", "you", "do", "?"], "pred": [["what", "are", "you", "doing", "?"], ["i", "don", "'t", "think", "so"], ["i", "?", "l", "be", "right", "back"], ["i", "?", "e", "got", "to", "go"], ["i", "?", "l", "take", "care", "of", "it"], ["i", "can", "'t", "believe", "it"], ["i", "can", "'t", "do", "that"], ["don", "'t", "worry", "about", "it"], ["i", "'m", "glad", "you", "'r", "e", "here"], ["what", "do", "you", "mean", "?"]], "scores": [-6.081773042678833, -7.545299828052521, -7.729363322257996, -8.655841052532196, -8.254530414938927, -8.216341227293015, -8.245259910821915, -8.297761380672455, -10.08485233783722, -6.32866907119751]}, {"input": ["what", "happened", "to", "your", "pants", "?"], "pred": [["what", "are", "you", "doing", "?"], ["i", "don", "'t", "think", "so"], ["what", "are", "you", "doing", "here", "?"], ["i", "?", "l", "tell", "you", "what"], ["what", "'s", "going", "on", "?"], ["you", "know", "what", "i", "mean", "?"], ["what", "'s", "the", "matter", "?"], ["are", "you", "all", "right", "?"], ["why", "didn", "'t", "you", "tell", "me", "?"], ["i", "?", "l", "be", "right", "back"]], "scores": [-5.344510555267334, -7.7986865639686584, -5.905178546905518, -8.865684449672699, -6.1368690729141235, -8.974892318248749, -5.620248913764954, -7.301467299461365, -9.37531390786171, -7.834514737129211]}, {"input": ["i", "just", "want", "the", "job", "."], "pred": [["i", "don", "'t", "want", "to"], ["i", "want", "to", "talk", "to", "you"], ["what", "do", "you", "want", "?"], ["i", "don", "'t", "think", "so"], ["i", "don", "'t", "want", "any", "trouble"], ["i", "don", "'t", "care", "what", "you", "say"], ["i", ".", "l", "be", "right", "back"], ["don", "'t", "worry", "about", "it"], ["what", "are", "you", "talking", "about", "?"], ["you", "know", "what", "i", "mean", "?"]], "scores": [-7.370992302894592, -8.374696284532547, -5.487936079502106, -7.488310813903809, -8.26405817270279, -9.104079276323318, -8.35349416732788, -7.497141271829605, -6.51925253868103, -8.446307599544525]}, {"input": ["where", "are", "you", "?"], "pred": [["where", "are", "you", "going", "?"], ["i", "don", "'t", "think", "so"], ["where", "do", "you", "think", "you", "'r", "e", "going", "?"], ["i", "don", "'t", "know", "what", "to", "say"], ["i", "?", "l", "be", "right", "back"], ["what", "do", "you", "want", "?"], ["i", "?", "l", "take", "care", "of", "it"], ["what", "'s", "the", "matter", "?"], ["i", "?", "e", "got", "to", "go"], ["don", "'t", "worry", "about", "it"]], "scores": [-4.794807553291321, -7.732100307941437, -8.470518589019775, -9.576965570449829, -7.457496523857117, -7.156000643968582, -8.912925019860268, -6.473385691642761, -9.018995523452759, -8.508162796497345]}, {"input": ["did", "you", "call", "?"], "pred": [["what", "are", "you", "doing", "here", "?"], ["i", "?", "l", "be", "right", "back"], ["it", "'s", "been", "a", "long", "time"], ["i", "don", "'t", "know", "what", "to", "say"], ["what", "'s", "the", "matter", "?"], ["why", "didn", "'t", "you", "tell", "me", "?"], ["what", "do", "you", "think", "you", "'r", "e", "doing", "?"], ["i", "don", "'t", "think", "so"], ["i", "didn", "'t", "mean", "to"], ["i", "can", "'t", "believe", "it"]], "scores": [-5.599084734916687, -7.8772454261779785, -9.443149328231812, -9.403549671173096, -5.903562426567078, -8.305849730968475, -9.314161479473114, -7.570958971977234, -8.994187355041504, -7.8203515112400055]}, {"input": ["who", "invited", "you", "?"], "pred": [["what", "are", "you", "doing", "here", "?"], ["i", "don", "'t", "want", "to"], ["i", "'m", "glad", "you", "'r", "e", "here"], ["i", "don", "'t", "think", "so"], ["i", "?", "l", "take", "care", "of", "it"], ["why", "didn", "'t", "you", "tell", "me", "?"], ["i", "?", "e", "got", "to", "go"], ["i", "?", "l", "be", "right", "back"], ["what", "do", "you", "want", "?"], ["what", "are", "you", "doing", "?"]], "scores": [-5.4011757373809814, -9.631381034851074, -9.083715558052063, -8.01241546869278, -9.257219895720482, -8.758027255535126, -9.201790690422058, -7.663108706474304, -6.610100597143173, -6.069301724433899]}, {"input": ["how", "far", "have", "you", "gotten", "?"], "pred": [["i", "can", "'t", "believe", "it"], ["i", "?", "e", "been", "looking", "for", "you"], ["what", "do", "you", "mean", "?"], ["i", "didn", "'t", "mean", "to"], ["i", "?", "l", "be", "right", "back"], ["i", "don", "'t", "think", "so"], ["i", "?", "e", "never", "seen", "anything", "like", "it"], ["how", "do", "you", "do", "?"], ["i", "?", "e", "got", "to", "go"], ["it", "'s", "been", "a", "long", "time"]], "scores": [-8.253346920013428, -9.17353242635727, -6.483472466468811, -9.549187421798706, -8.175735592842102, -7.775865793228149, -10.12793231010437, -7.1725247502326965, -9.92312490940094, -8.97613799571991]}, {"input": ["they", "'ve", "taken", "your", "clothes", "?"], "pred": [["what", "are", "you", "doing", "?"], ["i", "don", "'t", "think", "so"], ["i", "?", "e", "seen", "them"], ["they", "'r", "e", "all", "dead"], ["i", "?", "l", "be", "right", "back"], ["what", "do", "you", "mean", "?"], ["what", "'s", "the", "matter", "?"], ["i", "didn", "'t", "mean", "to"], ["what", "did", "they", "do", "to", "you", "?"], ["what", "are", "you", "doing", "here", "?"]], "scores": [-5.995387434959412, -8.223304510116577, -9.091539084911346, -9.133494973182678, -9.221666157245636, -6.019450783729553, -6.131691515445709, -9.988934338092804, -8.038904845714569, -6.037328720092773]}, {"input": ["he", "wants", "the", "money", "."], "pred": [["i", "want", "to", "talk", "to", "him"], ["what", "do", "you", "mean", "?"], ["i", "don", "'t", "think", "so"], ["what", "did", "he", "say", "?"], ["don", "'t", "worry", "about", "it"], ["he", "doesn", "'t", "know", "anything"], ["he", "wants", "to", "talk", "to", "you"], ["i", ".", "l", "tell", "you", "what"], ["what", "'s", "the", "matter", "?"], ["i", ".", "e", "got", "to", "go"]], "scores": [-9.253845751285553, -6.183449745178223, -7.894453346729279, -6.229065954685211, -8.539528012275696, -8.954479336738586, -8.553499072790146, -9.146863520145416, -7.0571324825286865, -10.603139519691467]}, {"input": ["what", "did", "you", "just", "say", "?"], "pred": [["what", "'s", "the", "matter", "?"], ["i", "don", "'t", "think", "so"], ["i", "?", "l", "be", "right", "back"], ["what", "are", "you", "talking", "about", "?"], ["i", "don", "'t", "know", "what", "to", "say"], ["i", "can", "'t", "believe", "it"], ["i", "didn", "'t", "mean", "to", "hurt", "you"], ["i", "didn", "'t", "mean", "to"], ["that", "'s", "what", "i", "said"], ["why", "didn", "'t", "you", "tell", "me", "?"]], "scores": [-6.352951765060425, -7.310769021511078, -8.041787385940552, -6.049219131469727, -8.584206461906433, -7.723525255918503, -9.543169379234314, -8.6661456823349, -9.101382791996002, -8.602158315479755]}, {"input": ["tell", "me", "your", "name", "."], "pred": [["what", "do", "you", "want", "?"], ["i", "don", "'t", "think", "so"], ["i", ".", "l", "be", "right", "back"], ["my", "name", "is", "your", "name"], ["what", "do", "you", "mean", "?"], ["i", ".", "l", "tell", "you", "what"], ["let", "me", "tell", "you", "something"], ["that", "'s", "why", "i", "'m", "here"], ["what", "are", "you", "doing", "here", "?"], ["you", "'r", "e", "a", "."]], "scores": [-5.959578692913055, -8.51917153596878, -8.454205989837646, -7.789736866950989, -6.373836517333984, -7.863759160041809, -7.583280473947525, -9.439418628811836, -6.781367897987366, -9.5339635014534]}, {"input": ["so", "what", "should", "i", "wear", "?"], "pred": [["you", "know", "what", "i", "mean", "?"], ["i", "can", "'t", "believe", "it"], ["you", "'r", "e", "a", "?"], ["i", "don", "'t", "think", "so"], ["i", "?", "l", "be", "right", "back"], ["i", "?", "l", "take", "care", "of", "it"], ["i", "?", "e", "been", "thinking"], ["what", "are", "you", "doing", "?"], ["i", "?", "e", "never", "seen", "anything", "like", "it"], ["i", "don", "'t", "know", "what", "to", "say"]], "scores": [-9.243282675743103, -8.047339677810669, -9.507598996162415, -7.547609716653824, -8.140973687171936, -9.712286502122879, -9.663410067558289, -7.493804156780243, -10.35478937625885, -9.297714114189148]}, {"input": ["are", "you", "nervous", "?"], "pred": [["i", "don", "'t", "think", "so"], ["don", "'t", "worry", "about", "it"], ["i", "'m", "glad", "you", "'r", "e", "here"], ["i", "?", "l", "be", "right", "back"], ["what", "are", "you", "doing", "?"], ["you", "'r", "e", "all", "right"], ["what", "'s", "the", "matter", "?"], ["what", "do", "you", "mean", "?"], ["i", "didn", "'t", "mean", "to"], ["i", "?", "e", "been", "thinking"]], "scores": [-7.11778599023819, -8.285934448242188, -9.027841806411743, -7.46259605884552, -5.013509511947632, -8.789233326911926, -5.782456874847412, -6.709728360176086, -9.47601169347763, -9.096765697002411]}, {"input": ["are", "you", "frightened", "?"], "pred": [["i", "?", "l", "be", "right", "back"], ["don", "'t", "worry", "about", "it"], ["what", "are", "you", "doing", "?"], ["are", "you", "all", "right", "?"], ["i", "don", "'t", "want", "to"], ["i", "don", "'t", "think", "so"], ["what", "'s", "the", "matter", "?"], ["i", "can", "'t", "believe", "it"], ["i", "?", "l", "be", "back"], ["it", "'s", "not", "my", "fault"]], "scores": [-7.944556832313538, -8.644759058952332, -5.21302330493927, -6.07197904586792, -9.533570528030396, -7.365008294582367, -6.169072151184082, -7.776724696159363, -9.185096859931946, -9.181644648313522]}, {"input": ["i", "hope", "he", "fell", "off", "."], "pred": [["i", "don", "'t", "think", "so"], ["what", "do", "you", "mean", "?"], ["i", ".", "e", "never", "seen", "him"], ["that", "'s", "a", "good", "idea"], ["what", "did", "he", "say", "?"], ["i", "didn", "'t", "see", "him"], ["i", ".", "l", "be", "right", "back"], ["i", ".", "e", "seen", "him"], ["i", "don", "'t", "know", "what", "to", "say"], ["i", "can", "'t", "believe", "it"]], "scores": [-7.795583009719849, -6.730280637741089, -10.140588641166687, -10.047947406768799, -7.311007559299469, -9.204066455364227, -9.00299060344696, -9.194645524024963, -9.71624481678009, -8.395384192466736]}, {"input": ["he", "was", "...", "taken", "."], "pred": [["i", "don", "'t", "think", "so"], ["what", "did", "he", "say", "?"], ["why", "didn", "'t", "you", "tell", "me", "?"], ["what", "do", "you", "mean", "?"], ["i", "didn", "'t", "know", "that"], ["i", ".", "e", "seen", "him"], ["what", "'s", "the", "matter", "?"], ["i", ".", "l", "be", "right", "back"], ["that", "'s", "what", "he", "said"], ["his", "name", "was", "...", "taken"]], "scores": [-8.580204129219055, -6.251179099082947, -9.398419380187988, -6.3297059535980225, -9.70110297203064, -9.773005247116089, -8.125258564949036, -10.234261512756348, -9.197174489498138, -9.352981090545654]}, {"input": ["why", "are", "you", "working", "today", "?"], "pred": [["i", "?", "l", "be", "right", "back"], ["i", "?", "e", "been", "thinking"], ["what", "are", "you", "doing", "here", "?"], ["i", "can", "'t", "believe", "it"], ["i", "don", "'t", "think", "so"], ["what", "'s", "the", "matter", "?"], ["what", "do", "you", "want", "?"], ["why", "didn", "'t", "you", "tell", "me", "?"], ["come", "on", "let", "'s", "go"], ["i", "want", "to", "talk", "to", "you"]], "scores": [-7.185099959373474, -8.915912330150604, -5.302966594696045, -8.300472974777222, -7.960088491439819, -6.111768364906311, -6.9319190084934235, -8.437108427286148, -8.05900752544403, -8.551692724227905]}, {"input": ["looking", "for", "intelligent", "life", "?"], "pred": [["what", "do", "you", "mean", "?"], ["what", "are", "you", "doing", "?"], ["i", "don", "'t", "think", "so"], ["what", "'s", "the", "matter", "?"], ["i", "?", "e", "been", "thinking"], ["that", "'s", "why", "i", "'m", "here"], ["you", "know", "what", "i", "mean", "?"], ["you", "?", "e", "got", "to", "be", "kidding", "me"], ["it", "'s", "been", "a", "long", "time"], ["what", "do", "you", "think", "?"]], "scores": [-5.843393564224243, -6.060892701148987, -7.903814435005188, -6.805216670036316, -9.04909634590149, -9.085352689027786, -8.999013900756836, -11.67700082063675, -10.266429901123047, -6.193612694740295]}, {"input": ["maybe", "you", "inspire", "me", "."], "pred": [["i", "don", "'t", "think", "so"], ["what", "do", "you", "mean", "?"], ["maybe", "you", "'r", "e", "right"], ["i", "don", "'t", "know", "why"], ["i", ".", "e", "never", "seen", "anything", "like", "it"], ["i", ".", "l", "be", "right", "back"], ["i", "don", "'t", "know", "you"], ["i", "don", "'t", "want", "to"], ["you", "know", "what", "i", "mean", "?"], ["that", "'s", "why", "i", "'m", "here"]], "scores": [-7.284429490566254, -6.460104823112488, -7.458345174789429, -8.560232162475586, -9.761232376098633, -8.758576512336731, -9.009631156921387, -10.155844628810883, -8.976037442684174, -9.049087911844254]}, {"input": ["i", "might", "do", "it", "wrong", "."], "pred": [["what", "do", "you", "mean", "?"], ["i", "don", "'t", "think", "so"], ["i", ".", "l", "be", "right", "back"], ["i", "don", "'t", "know", "why"], ["i", "can", "'t", "do", "that"], ["i", "don", "'t", "know", "what", "to", "say"], ["i", "don", "'t", "know", "what", "you", "mean"], ["i", "can", "'t", "believe", "it"], ["don", "'t", "worry", "about", "it"], ["you", "know", "what", "i", "mean", "?"]], "scores": [-6.387676358222961, -6.740474700927734, -9.175596117973328, -9.029788494110107, -8.391692221164703, -8.791546106338501, -9.50009024143219, -7.533222496509552, -7.819549918174744, -9.022142767906189]}, {"input": ["you", "okay", "?"], "pred": [["you", "'r", "e", "right"], ["i", "can", "'t", "believe", "it"], ["don", "'t", "worry", "about", "it"], ["i", "?", "e", "got", "to", "go"], ["what", "do", "you", "mean", "?"], ["i", "?", "l", "be", "right", "back"], ["i", "don", "'t", "know"], ["what", "are", "you", "doing", "?"], ["i", "don", "'t", "want", "to", "hurt", "you"], ["get", "out", "of", "here", "!"]], "scores": [-7.25762277841568, -7.984761089086533, -7.624346971511841, -8.802406251430511, -7.036440372467041, -8.160502195358276, -6.182033896446228, -6.314480543136597, -10.539020895957947, -6.953833341598511]}, {"input": ["are", "you", "alright", "?"], "pred": [["i", "?", "l", "be", "right", "back"], ["i", "can", "'t", "believe", "it"], ["i", "don", "'t", "think", "so"], ["i", "'m", "not", "going", "anywhere"], ["what", "are", "you", "doing", "?"], ["i", "'m", "glad", "you", "'r", "e", "here"], ["i", "don", "'t", "want", "to"], ["you", "'r", "e", "not", "going", "anywhere"], ["are", "you", "all", "right", "?"], ["don", "'t", "worry", "about", "it"]], "scores": [-7.49953693151474, -8.095512092113495, -7.4538931250572205, -9.294521927833557, -5.533485531806946, -9.208943903446198, -9.389498382806778, -9.734323740005493, -6.1140296459198, -8.29508975148201]}, {"input": ["good", "luck", "."], "pred": [["i", ".", "e", "been", "thinking"], ["you", "'r", "e", "right"], ["i", "don", "'t", "know"], ["what", "are", "you", "doing", "?"], ["i", ".", "l", "be", "right", "back"], ["let", "me", "tell", "you", "something"], ["don", "'t", "worry", "about", "it"], ["you", "know", "what", "i", "mean", "?"], ["get", "out", "of", "here", "!"], ["i", ".", "e", "got", "to", "go"]], "scores": [-9.143159449100494, -7.472755610942841, -6.710545301437378, -7.036003232002258, -8.210195541381836, -8.955240368843079, -7.589014530181885, -9.197598397731781, -7.374004304409027, -9.212523341178894]}, {"input": ["when", "do", "we", "go", "?"], "pred": [["i", "?", "l", "do", "it"], ["i", "don", "'t", "think", "so"], ["what", "do", "you", "think", "?"], ["we", "'r", "e", "on", "our", "way"], ["don", "'t", "worry", "about", "it"], ["i", "?", "e", "got", "to", "go"], ["i", "?", "l", "be", "right", "back"], ["that", "'s", "a", "good", "idea"], ["what", "'s", "the", "matter", "?"], ["i", "?", "l", "take", "care", "of", "it"]], "scores": [-8.741862118244171, -7.54145073890686, -6.704119920730591, -9.322617173194885, -8.683193385601044, -9.030465543270111, -7.570054292678833, -9.622125506401062, -7.6419957280159, -9.221714198589325]}, {"input": ["will", "he", "be", "alright", "?"], "pred": [["i", "?", "l", "be", "right", "back"], ["what", "do", "you", "mean", "?"], ["i", "don", "'t", "think", "so"], ["i", "?", "l", "take", "care", "of", "him"], ["i", "?", "l", "get", "him"], ["i", "want", "to", "see", "him"], ["i", "can", "'t", "believe", "it"], ["don", "'t", "worry", "about", "it"], ["he", "'s", "in", "the", "hospital"], ["he", "?", "l", "be", "all", "right"]], "scores": [-7.1521897315979, -7.191426515579224, -7.879207134246826, -8.867780089378357, -8.668780863285065, -9.3108971118927, -9.25505393743515, -7.97035014629364, -9.395277261734009, -7.51937498152256]}, {"input": ["jesus", "!", "are", "you", "serious", "?"], "pred": [["i", "don", "'t", "think", "so"], ["what", "are", "you", "doing", "?"], ["i", "don", "'t", "know", "!"], ["i", "?", "l", "be", "right", "back"], ["i", "'m", "glad", "you", "'r", "e", "here"], ["i", "can", "'t", "believe", "it"], ["i", "didn", "'t", "mean", "to"], ["i", "?", "e", "got", "to", "go"], ["i", "'m", "gonna", "kill", "you", "!"], ["get", "out", "of", "here", "!"]], "scores": [-7.965495526790619, -6.056115984916687, -8.7047598361969, -8.015164971351624, -10.585816323757172, -8.21269816160202, -9.970541954040527, -10.070192813873291, -10.356015682220459, -7.571983635425568]}, {"input": ["that", "'s", "coming", "along", "well", "!"], "pred": [["i", "!", "e", "got", "to", "go"], ["i", "don", "'t", "know", "!"], ["i", "!", "l", "take", "care", "of", "it"], ["they", "'r", "e", "coming", "!"], ["i", "!", "l", "be", "right", "back"], ["that", "'s", "a", "good", "idea"], ["what", "'s", "the", "matter", "?"], ["what", "are", "you", "doing", "?"], ["it", "'s", "good", "to", "see", "you"], ["i", "!", "e", "got", "to", "go", "!"]], "scores": [-9.44517719745636, -8.448445916175842, -9.116235494613647, -8.629819631576538, -8.05996036529541, -9.027283549308777, -6.976460933685303, -6.8924291133880615, -10.388343155384064, -10.199654221534729]}, {"input": ["poor", "father", ".", ".", "."], "pred": [["i", "don", "'t", "know", "why"], ["what", "do", "you", "mean", "?"], ["i", ".", "l", "be", "right", "back"], ["i", ".", "l", "tell", "you", "what"], ["i", "don", "'t", "think", "so"], ["what", "are", "you", "talking", "about", "?"], ["what", "'s", "the", "matter", "?"], ["how", "do", "you", "do", "?"], ["i", ".", "e", "been", "thinking"], ["that", "'s", "why", "i", "'m", "here"]], "scores": [-9.628692388534546, -6.171582102775574, -9.44421911239624, -9.675996899604797, -8.374678790569305, -6.920615553855896, -7.235785722732544, -7.536656320095062, -10.443666100502014, -9.787317991256714]}, {"input": ["i", "'m", "scared", "shitless", "."], "pred": [["i", "don", "'t", "know", "why"], ["what", "are", "you", "doing", "?"], ["i", "can", "'t", "believe", "it"], ["i", "'m", "not", "afraid", "of", "you"], ["what", "do", "you", "mean", "?"], ["i", "don", "'t", "think", "so"], ["i", ".", "e", "never", "seen", "anything", "like", "it"], ["what", "'s", "the", "matter", "?"], ["i", ".", "l", "be", "right", "back"], ["i", "'m", "glad", "you", "'r", "e", "here"]], "scores": [-8.100564420223236, -4.886817812919617, -7.793567061424255, -8.959228336811066, -6.017982602119446, -7.091598749160767, -10.024060010910034, -6.030634522438049, -8.345560193061829, -9.333754777908325]}, {"input": ["this", "thing", "'s", "going", "nowhere", "."], "pred": [["i", "don", "'t", "think", "so"], ["i", ".", "l", "be", "right", "back"], ["what", "are", "you", "doing", "?"], ["what", "are", "you", "going", "to", "do", "?"], ["don", "'t", "worry", "about", "it"], ["get", "out", "of", "here", "!"], ["what", "'s", "going", "on", "?"], ["you", "'r", "e", "not", "going", "anywhere"], ["that", "'s", "why", "i", "'m", "here"], ["you", "know", "what", "i", "mean", "?"]], "scores": [-7.622979998588562, -8.06027626991272, -5.422654867172241, -7.849458456039429, -7.8262659907341, -7.91866397857666, -6.193853259086609, -9.50973641872406, -9.660060748457909, -8.492247939109802]}, {"input": ["you", "know", "where", "he", "lives", "?"], "pred": [["i", "don", "'t", "know", "where", "he", "is"], ["what", "do", "you", "mean", "?"], ["i", "?", "e", "seen", "him"], ["i", "?", "l", "tell", "you", "what"], ["i", "don", "'t", "know", "!"], ["i", "?", "l", "be", "right", "back"], ["he", "'s", "a", "friend", "of", "mine"], ["i", "don", "'t", "know", "what", "to", "say"], ["what", "'s", "the", "matter", "?"], ["you", "know", "what", "i", "mean", "?"]], "scores": [-7.766061902046204, -6.570866942405701, -8.799852132797241, -8.743948876857758, -8.065961122512817, -8.465842008590698, -9.225742280483246, -9.41727900505066, -8.454475998878479, -8.367536783218384]}, {"input": ["i", "like", "cows", "."], "pred": [["i", "can", "'t", "believe", "it"], ["what", "are", "you", "doing", "?"], ["i", ".", "l", "be", "right", "back"], ["i", ".", "e", "never", "seen", "anything", "like", "it"], ["what", "do", "you", "mean", "?"], ["don", "'t", "worry", "about", "it"], ["i", ".", "e", "been", "thinking"], ["i", "don", "'t", "think", "so"], ["that", "'s", "why", "i", "'m", "here"], ["you", "know", "what", "i", "mean", "?"]], "scores": [-7.673973917961121, -6.391930162906647, -8.494136214256287, -9.707394480705261, -6.246993899345398, -8.82743901014328, -9.330414056777954, -7.551202714443207, -9.883144617080688, -8.186830818653107]}, {"input": ["you", "watch", "this", "garbage", "?"], "pred": [["i", "?", "l", "be", "right", "back"], ["i", "don", "'t", "think", "so"], ["what", "'s", "the", "matter", "?"], ["what", "are", "you", "doing", "?"], ["what", "do", "you", "think", "you", "'r", "e", "doing", "?"], ["what", "do", "you", "mean", "?"], ["come", "on", "let", "'s", "go"], ["i", "don", "'t", "know", "what", "to", "do"], ["you", "know", "what", "i", "mean", "?"], ["you", "don", "'t", "have", "to"]], "scores": [-7.92752993106842, -7.736519873142242, -6.300483226776123, -5.260478138923645, -8.759369969367981, -6.841851472854614, -8.381950750946999, -9.815608143806458, -8.470359146595001, -10.090225011110306]}, {"input": ["my", "wife", "wasn", "'t", "diabetic", "."], "pred": [["what", "do", "you", "mean", "?"], ["i", ".", "l", "be", "right", "back"], ["i", "can", "'t", "believe", "it"], ["i", "don", "'t", "think", "so"], ["why", "didn", "'t", "you", "tell", "me", "?"], ["i", "didn", "'t", "mean", "to"], ["i", ".", "e", "never", "seen", "anything", "like", "it"], ["that", "'s", "what", "i", "thought"], ["what", "'s", "the", "matter", "?"], ["what", "are", "you", "doing", "here", "?"]], "scores": [-6.346059441566467, -9.282724142074585, -8.614379644393921, -8.400055825710297, -8.958384916186333, -9.66997492313385, -10.575853824615479, -9.595050424337387, -7.037061929702759, -6.564535856246948]}, {"input": ["its", "muscles", "are", "locked", "."], "pred": [["it", "'s", "been", "a", "long", "time"], ["i", ".", "e", "seen", "it"], ["it", "'s", "a", ".", "locked"], ["what", "do", "you", "mean", "?"], ["i", "don", "'t", "think", "so"], ["it", "'s", "not", "a", "."], ["what", "are", "you", "doing", "?"], ["i", "can", "'t", "believe", "it"], ["it", "'s", "called", "a", "."], ["i", "don", "'t", "know", "what", "to", "do"]], "scores": [-10.20966124534607, -9.655794024467468, -8.913699746131897, -7.186446130275726, -8.683942198753357, -9.576057314872742, -7.109342455863953, -8.362736582756042, -9.967328190803528, -10.292012155056]}, {"input": ["it", "bit", "you", "."], "pred": [["what", "do", "you", "mean", "?"], ["i", "don", "'t", "think", "so"], ["what", "do", "you", "think", "you", "'r", "e", "doing", "?"], ["i", ".", "l", "be", "right", "back"], ["you", "know", "what", "i", "mean"], ["i", ".", "e", "seen", "it"], ["i", "don", "'t", "like", "it"], ["it", "'s", "not", "your", "fault"], ["don", "'t", "worry", "about", "it"], ["i", "can", "'t", "believe", "it"]], "scores": [-6.106188654899597, -7.183307588100433, -9.24663120508194, -8.592679500579834, -9.133166074752808, -9.516847133636475, -8.792500436306, -8.635798454284668, -8.29676365852356, -7.756515294313431]}, {"input": ["see", "anything", "you", "like", "?"], "pred": [["what", "'s", "the", "matter", "?"], ["i", "?", "l", "be", "right", "back"], ["i", "don", "'t", "think", "so"], ["i", "can", "'t", "believe", "it"], ["i", "?", "l", "take", "care", "of", "it"], ["i", "?", "e", "been", "looking", "all", "over", "for", "you"], ["you", "'r", "e", "all", "right"], ["i", "?", "e", "got", "to", "go"], ["come", "on", "let", "'s", "go"], ["i", "'d", "like", "to", "talk", "to", "you"]], "scores": [-6.215327739715576, -7.209076821804047, -7.504211366176605, -8.223261177539825, -8.8320814371109, -9.902858972549438, -8.971847891807556, -9.381211519241333, -7.796202138066292, -10.666997015476227]}, {"input": ["sorry", ",", "am", "i", "interrupting", "?"], "pred": [["i", "don", "'t", "think", "so"], ["i", "'m", "sorry", "i", "'m", "late"], ["i", "?", "l", "be", "right", "back"], ["i", "?", "e", "got", "to", "go"], ["can", "i", "help", "you", "?"], ["what", "do", "you", "mean", "?"], ["what", "are", "you", "doing", "here", "?"], ["come", "on", "let", "'s", "go"], ["sorry", "interrupting", "interrupting", "interrupting", "interrupting"], ["you", "?", "e", "got", "to", "be", "kidding", "me"]], "scores": [-7.935679078102112, -8.824541926383972, -7.705490350723267, -9.726033091545105, -7.614903211593628, -7.043078541755676, -6.653651595115662, -8.372079014778137, -10.213526368141174, -11.558461308479309]}, {"input": ["i", "'ve", "lost", "interest", "."], "pred": [["what", "are", "you", "doing", "here", "?"], ["i", "don", "'t", "think", "so"], ["what", "do", "you", "want", "?"], ["i", ".", "e", "been", "thinking"], ["what", "do", "you", "mean", "?"], ["why", "didn", "'t", "you", "tell", "me", "?"], ["what", "'s", "the", "matter", "?"], ["that", "'s", "why", "i", "'m", "here"], ["i", ".", "l", "be", "right", "back"], ["what", "are", "you", "doing", "?"]], "scores": [-5.738454222679138, -8.069231867790222, -6.606881499290466, -9.747194528579712, -5.6706342697143555, -8.567484512925148, -6.957129597663879, -9.491135358810425, -9.665028691291809, -6.120839238166809]}, {"input": ["what", "are", "you", "crying", "for", "?"], "pred": [["what", "are", "you", "doing", "?"], ["i", "don", "'t", "think", "so"], ["what", "do", "you", "mean", "?"], ["i", "thought", "you", "were", "dead"], ["i", "can", "'t", "believe", "it"], ["i", "?", "l", "kill", "you", "!"], ["what", "'s", "the", "matter", "?"], ["i", "?", "l", "be", "right", "back"], ["i", "'m", "glad", "you", "'r", "e", "here"], ["come", "on", "let", "'s", "go"]], "scores": [-4.660881280899048, -8.05393984913826, -6.689702033996582, -9.669271677732468, -8.08335018157959, -8.969213783740997, -5.66443943977356, -7.835599660873413, -9.909474849700928, -7.923310101032257]}, {"input": ["shall", "we", "unpack", "it", "?"], "pred": [["i", "?", "e", "got", "it"], ["i", "can", "'t", "believe", "it"], ["i", "?", "l", "be", "right", "back"], ["i", "?", "l", "see", "you", "later"], ["i", "?", "l", "take", "it"], ["come", "on", "let", "'s", "go"], ["how", "do", "you", "do", "?"], ["i", "don", "'t", "think", "so"], ["it", "'s", "good", "to", "see", "you"], ["i", "?", "e", "never", "seen", "anything", "like", "it"]], "scores": [-8.733916640281677, -8.770151734352112, -7.520312786102295, -8.452906370162964, -8.106300473213196, -8.314888596534729, -7.294310927391052, -7.734609484672546, -9.852498829364777, -10.915940523147583]}, {"input": ["ready", "to", "roll", ",", "partner", "?"], "pred": [["what", "do", "you", "want", "?"], ["i", "?", "l", "tell", "you", "what"], ["i", "?", "l", "be", "right", "back"], ["what", "'s", "going", "on", "?"], ["i", "don", "'t", "think", "so"], ["what", "are", "you", "doing", "?"], ["i", "?", "e", "got", "to", "go"], ["i", "don", "'t", "know", "what", "to", "say"], ["that", "'s", "a", "good", "idea"], ["let", "'s", "get", "out", "of", "here"]], "scores": [-6.414721965789795, -9.190421164035797, -8.002567410469055, -6.5333627462387085, -8.874570667743683, -6.315822243690491, -10.240549921989441, -11.063604831695557, -9.42916339635849, -8.19533634185791]}, {"input": ["you", "going", "to", "answer", "it", "?"], "pred": [["what", "do", "you", "mean", "?"], ["i", "don", "'t", "believe", "it"], ["what", "are", "you", "going", "to", "do", "?"], ["i", "don", "'t", "think", "so"], ["i", "?", "l", "tell", "you", "what"], ["what", "are", "you", "talking", "about", "?"], ["what", "'s", "the", "matter", "?"], ["i", "?", "e", "got", "to", "go"], ["you", "don", "'t", "know", "what", "you", "'r", "e", "doing"], ["how", "do", "you", "know", "?"]], "scores": [-5.590187191963196, -8.349510252475739, -7.576627850532532, -7.916369438171387, -8.607784152030945, -5.8750996589660645, -5.783532440662384, -10.163831055164337, -11.761006712913513, -7.42656397819519]}, {"input": ["do", "you", "really", "know", "superman", "?"], "pred": [["i", "think", "you", "'r", "e", "right"], ["what", "do", "you", "mean", "?"], ["i", "don", "'t", "think", "so"], ["i", "don", "'t", "know", "what", "to", "say"], ["i", "?", "e", "been", "thinking"], ["i", "don", "'t", "know", "what", "you", "mean"], ["what", "'s", "the", "matter", "?"], ["i", "can", "'t", "believe", "it"], ["that", "'s", "why", "i", "'m", "here"], ["i", "?", "l", "be", "right", "back"]], "scores": [-9.896679282188416, -6.011771559715271, -7.499209523200989, -9.223225831985474, -9.673774480819702, -9.679531127214432, -8.202350497245789, -7.9828512370586395, -9.531885236501694, -8.972834944725037]}, {"input": ["how", "did", "it", "go", "today", "?"], "pred": [["i", "?", "l", "be", "right", "back"], ["don", "'t", "worry", "about", "it"], ["i", "don", "'t", "think", "so"], ["i", "?", "e", "got", "to", "go"], ["what", "are", "you", "doing", "?"], ["how", "did", "you", "know", "?"], ["that", "'s", "a", "good", "idea"], ["what", "'s", "the", "matter", "?"], ["i", "can", "'t", "believe", "it"], ["i", "?", "l", "get", "it"]], "scores": [-7.828383088111877, -8.658345729112625, -7.779190719127655, -9.373985528945923, -6.8678213357925415, -8.257219195365906, -9.708940207958221, -6.767461180686951, -7.784195601940155, -8.685718059539795]}, {"input": ["your", "ideas", "never", "work", "out", "."], "pred": [["i", "don", "'t", "know", "what", "to", "say"], ["what", "do", "you", "mean", "?"], ["you", "'r", "e", "a", "."], ["i", "don", "'t", "think", "so"], ["i", ".", "e", "been", "thinking"], ["i", ".", "l", "tell", "you", "what"], ["you", "don", "'t", "have", "to", "do", "that"], ["that", "'s", "why", "i", "'m", "here"], ["you", "know", "what", "i", "mean", "?"], ["i", "don", "'t", "know", "what", "you", "mean"]], "scores": [-9.135226368904114, -5.976131558418274, -8.951634764671326, -7.999949216842651, -9.020400643348694, -8.951960504055023, -11.023095786571503, -9.590787082910538, -8.641240239143372, -9.174898773431778]}, {"input": ["chief", "-", "mind", "if", "i", "take", "her", "?"], "pred": [["i", "?", "e", "got", "to", "go"], ["i", "?", "l", "take", "care", "of", "it"], ["i", "don", "'t", "want", "to"], ["i", "don", "'t", "think", "so"], ["i", "want", "to", "see", "her"], ["i", "?", "l", "be", "right", "back"], ["what", "are", "you", "doing", "?"], ["you", "?", "e", "got", "to", "help", "me"], ["what", "do", "you", "mean", "?"], ["let", "'s", "get", "out", "of", "here"]], "scores": [-9.02964699268341, -8.579355508089066, -10.091392993927002, -7.491014361381531, -9.662153601646423, -7.735867857933044, -6.85013735294342, -10.684748709201813, -7.097332835197449, -8.507668495178223]}, {"input": ["go", "ahead", "to", "the", "saloon", ".", "but", "don", "'t", "get", "too", "drunk", "!"], "pred": [["i", "!", "l", "be", "right", "back"], ["i", "don", "'t", "know", "!"], ["i", "!", "e", "got", "to", "go"], ["what", "are", "you", "doing", "?"], ["get", "out", "of", "here", "!"], ["you", "'r", "e", "not", "going", "anywhere"], ["what", "'s", "the", "matter", "?"], ["i", "don", "'t", "know", "what", "to", "say"], ["i", "!", "e", "had", "enough", "!"], ["i", "!", "l", "show", "you"]], "scores": [-8.578508973121643, -8.466512322425842, -9.35371446609497, -6.493758320808411, -7.121995985507965, -10.817417442798615, -6.888582766056061, -10.559292197227478, -9.161737859249115, -9.467699646949768]}, {"input": ["fine", "speech", ".", "now", "what", "do", "we", "do", "?"], "pred": [["what", "do", "you", "mean", "?"], ["i", "?", "l", "be", "right", "back"], ["i", "don", "'t", "know", "what", "to", "say"], ["i", "don", "'t", "think", "so"], ["that", "'s", "a", "good", "idea"], ["come", "on", "let", "'s", "go"], ["i", "?", "l", "do", "it"], ["i", "want", "to", "talk", "to", "you"], ["i", "don", "'t", "believe", "it"], ["speech", "do", "do", "do", "do", "do"]], "scores": [-7.218598008155823, -8.484466075897217, -10.241689801216125, -8.001315355300903, -9.861332535743713, -8.388752818107605, -9.17961871623993, -10.299265205860138, -9.087691724300385, -10.624845087528229]}, {"input": ["are", "you", "sure", "you", "even", "packed", "it", "?"], "pred": [["i", "don", "'t", "think", "so"], ["what", "do", "you", "mean", "?"], ["i", "?", "l", "be", "right", "back"], ["i", "'m", "in", "a", "hurry"], ["i", "?", "e", "been", "thinking"], ["i", "?", "e", "never", "seen", "anything", "like", "it"], ["you", "don", "'t", "have", "to", "worry"], ["i", "?", "e", "got", "it"], ["it", "'s", "been", "a", "long", "time"], ["that", "'s", "a", "good", "idea"]], "scores": [-7.602853894233704, -6.926140069961548, -8.078871250152588, -9.42825710773468, -9.43949007987976, -9.687027335166931, -11.73037001490593, -9.038157939910889, -9.504823207855225, -9.363338232040405]}, {"input": ["maybe", "it", "went", "out", ".", "should", "someone", "check", "it", "?"], "pred": [["i", "can", "'t", "believe", "it"], ["i", "don", "'t", "think", "so"], ["why", "didn", "'t", "you", "tell", "me", "?"], ["i", "don", "'t", "get", "it"], ["that", "'s", "not", "the", "point"], ["i", "think", "it", "'s", "someone"], ["what", "do", "you", "mean", "?"], ["i", "?", "e", "never", "seen", "anything", "like", "it"], ["i", "?", "e", "seen", "it"], ["i", "?", "l", "tell", "you", "what"]], "scores": [-7.670224130153656, -6.961903929710388, -9.12908399105072, -7.781821310520172, -9.279950380325317, -10.029828369617462, -6.98530375957489, -9.843134999275208, -9.354361295700073, -10.153140604496002]}, {"input": ["the", "bourbon", ".", "the", "news", "about", "ugarte", "upset", "me", "very", "much", "."], "pred": [["i", ".", "l", "be", "right", "back"], ["i", "can", "'t", "believe", "it"], ["what", "do", "you", "mean", "?"], ["i", "'m", "sorry", "i", "'m", "late"], ["what", "'s", "the", "matter", "?"], ["i", "don", "'t", "want", "to"], ["it", "'s", "been", "a", "long", "time"], ["i", "'m", "glad", "you", "'r", "e", "here"], ["i", "don", "'t", "think", "so"], ["i", ".", "e", "been", "thinking"]], "scores": [-8.672080039978027, -8.948519945144653, -7.04735791683197, -9.365028977394104, -6.636278390884399, -10.956810265779495, -10.140084862709045, -9.668126046657562, -8.003895342350006, -9.924363017082214]}, {"input": ["well", "i", "was", "right", ".", "you", "are", "a", "sentimentalist", "."], "pred": [["what", "are", "you", "talking", "about", "?"], ["i", "don", "'t", "think", "so"], ["what", "do", "you", "mean", "?"], ["what", "do", "you", "think", "you", "'r", "e", "doing", "?"], ["why", "didn", "'t", "you", "tell", "me", "?"], ["i", "didn", "'t", "say", "that"], ["i", ".", "l", "be", "right", "back"], ["how", "do", "you", "do", "?"], ["i", ".", "e", "never", "seen", "anything", "like", "it"], ["that", "'s", "why", "i", "'m", "here"]], "scores": [-6.334473371505737, -7.987650811672211, -5.978620648384094, -9.30275171995163, -8.862855106592178, -9.019761204719543, -9.432911932468414, -7.351170003414154, -11.146134972572327, -9.79724070429802]}, {"input": ["he", "thinks", "people", "*like*", "to", "get", "whacked", "by", "branches", "."], "pred": [["that", "'s", "what", "he", "said"], ["i", "don", "'t", "know", "why"], ["what", "does", "that", "mean", "?"], ["he", "doesn", "'t", "know", "anything"], ["how", "do", "you", "know", "?"], ["what", "do", "you", "mean", "?"], ["i", "don", "'t", "think", "so"], ["i", "don", "'t", "know", "what", "to", "say"], ["what", "'s", "going", "on", "?"], ["i", ".", "l", "tell", "you", "what"]], "scores": [-9.251701414585114, -9.221314430236816, -6.140030026435852, -8.87564468383789, -7.859847545623779, -6.005129456520081, -7.981388449668884, -9.830751657485962, -7.474123001098633, -9.432790279388428]}, {"input": ["you", "ain", "'t", "gettin", "'", "in", "no", "trouble", ",", "i", "hope", "."], "pred": [["i", "don", "'t", "think", "so"], ["what", "do", "you", "mean", "?"], ["what", "do", "you", "think", "you", "'r", "e", "doing", "?"], ["what", "'s", "going", "on", "?"], ["i", "ain", "'t", "goin", "nowhere"], ["i", ".", "l", "be", "right", "back"], ["i", ".", "l", "tell", "you", "what"], ["what", "'s", "the", "matter", "?"], ["don", "'t", "worry", "about", "it"], ["you", "know", "what", "i", "mean", "?"]], "scores": [-8.210277915000916, -7.532219886779785, -9.267847031354904, -7.660463333129883, -9.753409624099731, -8.948903203010559, -8.746870219707489, -6.866586804389954, -8.672577649354935, -8.77469915151596]}, {"input": ["now", "i", "think", "we", "really", "do", "understand", "one", "another", "."], "pred": [["i", "don", "'t", "know", "why"], ["i", "think", "you", "'r", "e", "right"], ["i", "don", "'t", "think", "so"], ["i", "don", "'t", "know", "what", "to", "say"], ["that", "'s", "what", "i", "thought"], ["it", "'s", "been", "a", "long", "time"], ["i", ".", "e", "been", "thinking"], ["i", ".", "l", "tell", "you", "what"], ["what", "do", "you", "mean", "?"], ["i", "don", "'t", "know", "what", "you", "mean"]], "scores": [-10.161835670471191, -10.079567551612854, -7.481148719787598, -9.464771389961243, -9.481439918279648, -10.57203984260559, -9.721793055534363, -10.23170018196106, -7.774626851081848, -10.766621172428131]}, {"input": ["i", "'m", "in", "a", "wheelchair", ",", "the", "truck", "sounds", "pretty", "good", "."], "pred": [["i", "don", "'t", "think", "so"], ["what", "are", "you", "doing", "?"], ["what", "are", "you", "doing", "here", "?"], ["i", ".", "l", "be", "right", "back"], ["what", "do", "you", "mean", "?"], ["what", "'s", "the", "matter", "?"], ["you", "know", "what", "i", "mean", "?"], ["i", "'m", "in", "a", "hurry"], ["what", "do", "you", "know", "about", "truck", "?"], ["i", ".", "e", "never", "seen", "anything", "like", "it"]], "scores": [-7.8678746819496155, -4.7484519481658936, -4.66538667678833, -8.231544733047485, -5.419844388961792, -6.159807205200195, -7.739864349365234, -8.263568371534348, -9.152141988277435, -10.237948536872864]}, {"input": ["don", "'t", "you", "think", "you", "should", "at", "least", "wave", "?"], "pred": [["i", "don", "'t", "want", "to", "die"], ["i", "?", "l", "be", "right", "back"], ["i", "don", "'t", "know", "what", "to", "say"], ["i", "don", "'t", "think", "so"], ["i", "think", "you", "'r", "e", "right"], ["what", "are", "you", "doing", "?"], ["i", "?", "e", "got", "to", "go"], ["what", "'s", "the", "matter", "?"], ["that", "'s", "why", "i", "'m", "here"], ["i", "don", "'t", "want", "to"]], "scores": [-9.338176220655441, -7.860835552215576, -9.239628076553345, -6.8617554903030396, -9.510025799274445, -6.53039014339447, -9.767517983913422, -6.567581415176392, -9.623218566179276, -9.600261241197586]}, {"input": ["ssh", ".", "i", "'m", "on", "a", "stakeout", "."], "pred": [["i", "can", "'t", "believe", "it"], ["i", ".", "e", "got", "to", "go"], ["where", "are", "you", "going", "?"], ["i", ".", "l", "be", "right", "back"], ["i", "'m", "glad", "you", "'r", "e", "here"], ["what", "are", "you", "doing", "?"], ["i", "don", "'t", "think", "so"], ["i", "don", "'t", "want", "to"], ["that", "'s", "why", "i", "'m", "here"], ["what", "'s", "the", "matter", "?"]], "scores": [-8.914153456687927, -10.161613702774048, -6.860388875007629, -8.570010542869568, -9.844142019748688, -6.206284165382385, -8.196200489997864, -10.730328232049942, -9.274322479963303, -7.12811005115509]}, {"input": ["look", ",", "nobody", "knows", "we", "did", "it", "."], "pred": [["i", "don", "'t", "know", "why"], ["what", "do", "you", "mean", "?"], ["i", "don", "'t", "think", "so"], ["how", "do", "you", "know", "that", "?"], ["i", ".", "l", "tell", "you", "what"], ["what", "'s", "the", "matter", "?"], ["it", "'s", "been", "a", "long", "time"], ["that", "'s", "not", "the", "point"], ["no", "no", "no", "no", "no"], ["i", "didn", "'t", "say", "that"]], "scores": [-9.05957567691803, -6.478726863861084, -7.604736328125, -9.2902512550354, -9.428564369678497, -7.950717926025391, -10.152136087417603, -9.349857151508331, -8.970919370651245, -9.3151353597641]}, {"input": ["does", "he", "have", "the", "marked", "bills", "on", "him", "?"], "pred": [["what", "do", "you", "mean", "?"], ["i", "don", "'t", "think", "so"], ["he", "doesn", "'t", "know", "anything"], ["i", "?", "e", "seen", "him"], ["i", "can", "'t", "believe", "it"], ["what", "are", "you", "talking", "about", "?"], ["don", "'t", "worry", "about", "it"], ["we", "?", "e", "got", "to", "find", "him"], ["what", "does", "that", "mean", "?"], ["he", "'s", "on", "his", "way"]], "scores": [-6.415900230407715, -8.378271341323853, -9.532066345214844, -10.173263192176819, -8.91789424419403, -8.252950310707092, -9.437970042228699, -10.89952465891838, -7.4539825320243835, -10.115351438522339]}, {"input": ["tonight", "turned", "out", "to", "be", "pretty", "interesting", "."], "pred": [["i", "don", "'t", "think", "so"], ["i", ".", "l", "tell", "you", "what"], ["i", ".", "e", "been", "thinking"], ["what", "are", "you", "doing", "here", "?"], ["i", "can", "'t", "believe", "it"], ["i", "'m", "glad", "you", "'r", "e", "here"], ["i", ".", "l", "be", "right", "back"], ["i", ".", "e", "been", "looking", "all", "over", "for", "you"], ["it", "'s", "been", "a", "long", "time"], ["that", "'s", "what", "i", "thought"]], "scores": [-8.247489035129547, -8.913221001625061, -8.715304613113403, -7.166292786598206, -8.66308206319809, -9.467198967933655, -8.006978034973145, -10.159820079803467, -9.452972412109375, -9.397119224071503]}, {"input": ["i", "forgot", "where", "i", "put", "my", "keys", "."], "pred": [["i", ".", "l", "be", "right", "back"], ["what", "are", "you", "doing", "?"], ["i", "don", "'t", "know", "why"], ["what", "do", "you", "mean", "?"], ["where", "did", "you", "get", "this", "?"], ["i", "don", "'t", "think", "so"], ["i", "can", "'t", "believe", "it"], ["i", ".", "e", "been", "looking", "for", "you"], ["why", "didn", "'t", "you", "tell", "me", "?"], ["what", "'s", "the", "matter", "?"]], "scores": [-7.830758094787598, -5.693331360816956, -9.469088912010193, -7.0505698919296265, -7.804728865623474, -8.311936676502228, -8.104443192481995, -9.954393684864044, -9.140124313533306, -7.041011810302734]}, {"input": ["i", "was", "holding", "for", "someone", ".", "that", "wasn", "'t", "even", "mine", "."], "pred": [["i", "can", "'t", "believe", "it"], ["what", "are", "you", "doing", "here", "?"], ["why", "didn", "'t", "you", "tell", "me", "?"], ["that", "'s", "what", "i", "thought"], ["i", "thought", "you", "were", "dead"], ["it", "'s", "been", "a", "long", "time"], ["i", "didn", "'t", "mean", "to"], ["i", "don", "'t", "think", "so"], ["i", ".", "e", "been", "looking", "for", "you"], ["it", "wasn", "'t", "my", "fault"]], "scores": [-8.272184610366821, -6.495523452758789, -8.333743423223495, -9.14557608962059, -8.91924113035202, -10.059102177619934, -9.092615604400635, -8.500925898551941, -10.720759391784668, -8.803920835256577]}, {"input": ["i", "'d", "love", "to", "drive", "through", "new", "england", "in", "the", "fall", "."], "pred": [["i", "don", "'t", "think", "so"], ["what", "do", "you", "think", "?"], ["i", "'d", "like", "to", "go", "home"], ["you", "know", "what", "i", "mean", "?"], ["i", "don", "'t", "know", "what", "to", "say"], ["i", "don", "'t", "want", "to"], ["i", ".", "l", "be", "right", "back"], ["i", ".", "l", "be", "back", "in", "a", "minute"], ["that", "'s", "a", "good", "idea"], ["when", "i", "was", "a", "kid"]], "scores": [-9.026637434959412, -7.676068007946014, -10.239316940307617, -9.468177080154419, -9.65855348110199, -10.201767176389694, -9.519192099571228, -11.584540963172913, -9.821647047996521, -9.104050159454346]}, {"input": ["he", "certainly", "was", "not", "a", "popular", "fellow", "when", "they", "planted", "him", "."], "pred": [["i", ".", "e", "heard", "of", "him"], ["i", "don", "'t", "know", "sir"], ["let", "me", "tell", "you", "something"], ["he", "was", "a", "good", "man"], ["i", "don", "'t", "think", "so"], ["his", "name", "was", "they", "him"], ["what", "do", "you", "mean", "?"], ["i", "don", "'t", "believe", "it"], ["that", "'s", "what", "he", "said"], ["i", ".", "e", "never", "seen", "him", "before"]], "scores": [-10.415267765522003, -9.759190082550049, -9.82697182893753, -8.870805859565735, -8.370521545410156, -10.250638484954834, -7.7556312084198, -9.849187016487122, -10.130142778158188, -11.025506883859634]}, {"input": ["why", "would", "he", "go", "to", "odessa", "?"], "pred": [["why", "didn", "'t", "you", "tell", "me", "?"], ["why", "would", "he", "do", "that", "?"], ["i", "don", "'t", "know", "where", "he", "is"], ["he", "didn", "'t", "have", "to"], ["i", "don", "'t", "think", "so"], ["what", "do", "you", "mean", "?"], ["i", "?", "e", "never", "seen", "him"], ["i", "don", "'t", "know", "what", "you", "mean"], ["that", "'s", "what", "he", "said"], ["i", "?", "l", "tell", "you", "what"]], "scores": [-8.953034818172455, -6.912342220544815, -10.489734053611755, -10.395029067993164, -8.008118271827698, -6.727825820446014, -11.070420682430267, -11.86677074432373, -9.54422253370285, -10.69041907787323]}, {"input": ["it", "'s", "okay", ".", "it", "'s", "alright", "."], "pred": [["don", "'t", "worry", "about", "it"], ["i", "don", "'t", "know", "what", "to", "say"], ["i", ".", "l", "be", "right", "back"], ["what", "are", "you", "doing", "?"], ["what", "'s", "the", "matter", "?"], ["i", "don", "'t", "think", "so"], ["i", ".", "e", "got", "it"], ["you", ".", "e", "got", "to", "help", "me"], ["i", ".", "e", "never", "seen", "anything", "like", "it"], ["i", "don", "'t", "want", "it"]], "scores": [-8.548400640487671, -9.169993996620178, -8.056194722652435, -6.254831910133362, -6.518967986106873, -7.379288613796234, -9.264063715934753, -11.23343676328659, -10.41111046075821, -9.277535319328308]}, {"input": ["yes", "...", "..we", "do", "ask", "for", "...", ".30", "to", "60", "days", "...", "."], "pred": [["i", "don", "'t", "know", "why"], ["what", "do", "you", "mean", "?"], ["i", ".", "l", "be", "right", "back"], ["what", "do", "you", "want", "?"], ["i", "don", "'t", "think", "so"], ["what", "do", "you", "think", "you", "'r", "e", "doing", "?"], ["i", "don", "'t", "know", "what", "to", "say"], ["that", "'s", "why", "i", "'m", "here"], ["do", "you", "know", "why", "?"], ["i", "'d", "like", "to", "ask", "you", "something"]], "scores": [-9.77570390701294, -6.71259605884552, -9.73411363363266, -7.739614248275757, -8.259419918060303, -10.177104890346527, -10.496808886528015, -10.026787459850311, -9.062982708215714, -12.027324110269547]}, {"input": ["i", "almost", "thought", "for", "a", "second", "..."], "pred": [["i", "don", "'t", "think", "so"], ["i", "...", "l", "be", "right", "back"], ["i", "'m", "in", "a", "hurry"], ["what", "are", "you", "doing", "?"], ["how", "did", "you", "know", "?"], ["what", "'s", "the", "matter", "?"], ["what", "do", "you", "mean", "?"], ["i", "...", "e", "never", "seen", "anything", "like", "it"], ["that", "'s", "what", "i", "thought"], ["it", "'s", "been", "a", "long", "time"]], "scores": [-7.707576394081116, -7.928759813308716, -9.240785717964172, -5.909088373184204, -8.988478422164917, -6.763972878456116, -6.872955560684204, -10.425724029541016, -9.239986538887024, -9.156510293483734]}, {"input": ["what", "'s", "he", "get", "if", "he", "wins", "here", "?"], "pred": [["he", "?", "l", "be", "all", "right"], ["i", "don", "'t", "think", "so"], ["what", "do", "you", "think", "?"], ["i", "?", "e", "got", "to", "go"], ["i", "?", "e", "got", "him"], ["he", "'s", "got", "a", "gun"], ["you", "?", "e", "got", "to", "be", "kidding", "me"], ["what", "'s", "the", "matter", "?"], ["what", "the", "hell", "is", "he", "doing", "?"], ["i", "?", "l", "be", "right", "back"]], "scores": [-8.660390585660934, -7.867745995521545, -7.1969141364097595, -10.196021497249603, -9.499850571155548, -8.75815349817276, -11.566500514745712, -7.490290284156799, -9.449478387832642, -8.978139281272888]}, {"input": ["i", "'m", "supposed", "to", "speak", "at", "their", "tenth", "anniversary", "."], "pred": [["what", "do", "you", "mean", "?"], ["i", "don", "'t", "think", "so"], ["what", "are", "you", "doing", "?"], ["i", "'m", "in", "a", "hurry"], ["i", ".", "e", "been", "thinking"], ["i", ".", "l", "be", "right", "back"], ["i", ".", "e", "never", "seen", "anything", "like", "it"], ["that", "'s", "why", "i", "'m", "here"], ["what", "'s", "going", "on", "?"], ["what", "do", "you", "think", "?"]], "scores": [-6.552692294120789, -7.8958200216293335, -5.698710560798645, -8.89142370223999, -9.35075831413269, -8.318746566772461, -10.581259608268738, -9.410905599594116, -6.808615684509277, -7.351785480976105]}, {"input": ["when", "you", "get", "going", "on", "those", "broads", ",", "think", "of", "me", "!"], "pred": [["what", "are", "you", "talking", "about", "?"], ["i", "!", "l", "be", "right", "back"], ["i", "don", "'t", "think", "so"], ["what", "do", "you", "mean", "?"], ["i", "!", "l", "tell", "you", "what"], ["i", "can", "'t", "believe", "it", "!"], ["what", "do", "you", "think", "you", "'r", "e", "doing", "?"], ["i", "!", "e", "got", "to", "go"], ["you", "know", "what", "i", "mean", "?"], ["what", "are", "you", "doing", "?"]], "scores": [-6.287052273750305, -8.361508250236511, -8.070810735225677, -7.329614698886871, -8.340324878692627, -8.647602021694183, -8.705638453364372, -10.110901236534119, -8.6424161195755, -6.422285079956055]}, {"input": ["c'mon", ",", "i", "need", "to", "talk", "to", "you", ".", "just", "the", "two", "of", "us", "."], "pred": [["i", ".", "l", "be", "right", "back"], ["what", "are", "you", "doing", "?"], ["what", "do", "you", "mean", "?"], ["i", "don", "'t", "think", "so"], ["i", "don", "'t", "know", "why"], ["that", "'s", "why", "i", "'m", "here"], ["i", ".", "e", "got", "to", "go"], ["i", ".", "l", "tell", "you", "what"], ["i", ".", "e", "had", "enough"], ["let", "'s", "get", "out", "of", "here"]], "scores": [-8.475289404392242, -6.555552005767822, -6.7029372453689575, -8.034233331680298, -9.718681931495667, -9.675365060567856, -10.346441090106964, -9.294919550418854, -10.32774007320404, -8.698868185281754]}, {"input": ["it", "might", "be", "an", "interesting", "case", "."], "pred": [["what", "do", "you", "mean", "?"], ["i", "don", "'t", "think", "so"], ["i", "don", "'t", "know", "what", "you", "'r", "e", "talking", "about"], ["i", ".", "l", "be", "right", "back"], ["i", "'d", "like", "to", "know"], ["i", "don", "'t", "know", "what", "to", "say"], ["i", ".", "e", "never", "seen", "anything", "like", "it"], ["i", ".", "e", "been", "thinking"], ["i", "can", "'t", "believe", "it"], ["what", "do", "you", "think", "?"]], "scores": [-6.383002161979675, -7.270054459571838, -9.165600061416626, -8.73345696926117, -10.61402553319931, -9.300758361816406, -10.507434487342834, -9.121036887168884, -8.6342853307724, -6.7082995772361755]}, {"input": ["it", "'s", "happened", "at", "last", ",", "we", "'ve", "become", "a", "limited", "company", "."], "pred": [["i", "don", "'t", "know", "why"], ["that", "'s", "why", "i", "'m", "here"], ["i", ".", "e", "been", "thinking"], ["i", ".", "l", "be", "right", "back"], ["what", "do", "you", "mean", "?"], ["i", "don", "'t", "think", "so"], ["what", "are", "you", "talking", "about", "?"], ["you", "know", "what", "i", "mean", "?"], ["i", "can", "'t", "believe", "it"], ["i", "don", "'t", "know", "what", "to", "say"]], "scores": [-9.818625092506409, -9.895565032958984, -9.392841219902039, -9.428074955940247, -6.35334575176239, -7.829338550567627, -7.126945495605469, -9.577836990356445, -8.890828728675842, -9.879217624664307]}, {"input": ["that", "'s", "right", ";", "convict", "without", "trial", "...", "habeas", "corpus", "."], "pred": [["what", "do", "you", "mean", "?"], ["i", "don", "'t", "think", "so"], ["that", "'s", "not", "the", "point"], ["you", "don", "'t", "have", "to"], ["that", "'s", "a", "good", "question"], ["you", "'r", "e", "under", "arrest"], ["i", ".", "e", "never", "seen", "anything", "like", "it"], ["i", ".", "l", "be", "right", "back"], ["i", ".", "l", "tell", "you", "what"], ["i", "'d", "like", "to", "ask", "you", "a", "few", "questions"]], "scores": [-6.123842000961304, -8.352500140666962, -9.527684390544891, -11.065421551465988, -9.547847926616669, -9.044015645980835, -11.917462468147278, -9.537535190582275, -9.506881952285767, -11.768650084733963]}, {"input": ["honey", ",", "we", "can", "be", "happy", "and", "poor", "together", "."], "pred": [["i", "can", "'t", "believe", "it"], ["what", "do", "you", "mean", "?"], ["i", "'m", "glad", "you", "'r", "e", "here"], ["i", ".", "l", "be", "right", "back"], ["i", "don", "'t", "think", "so"], ["i", "'m", "glad", "you", "came"], ["i", ".", "l", "tell", "you", "what"], ["you", "know", "what", "i", "mean", "?"], ["i", ".", "e", "got", "to", "go"], ["i", "don", "'t", "know", "what", "to", "say"]], "scores": [-8.408440679311752, -6.831196308135986, -9.82536393404007, -8.979444801807404, -7.987421154975891, -10.344361901283264, -9.61587792634964, -9.599558770656586, -10.944511651992798, -9.382911562919617]}, {"input": ["you", "'re", "the", "guys", "from", "the", "movie", "!"], "pred": [["you", "'r", "e", "kidding", "!"], ["i", "don", "'t", "know", "what", "to", "say"], ["what", "are", "you", "doing", "?"], ["i", "don", "'t", "know", "!"], ["i", "!", "l", "be", "right", "back"], ["what", "'s", "going", "on", "?"], ["what", "do", "you", "mean", "?"], ["i", "don", "'t", "want", "to"], ["what", "'s", "the", "matter", "?"], ["you", "'r", "e", "a", "genius", "!"]], "scores": [-8.219701409339905, -9.558682560920715, -5.746398448944092, -7.429981231689453, -8.625848829746246, -6.9116363525390625, -6.471928119659424, -10.627411723136902, -6.368273735046387, -9.162866652011871]}, {"input": ["there", "are", "cables", "overhead", ".", "hang", "on", ".", "it", "'ll", "clear", "up", "."], "pred": [["what", "do", "you", "mean", "?"], ["i", "don", "'t", "know", "what", "to", "say"], ["what", "are", "you", "doing", "?"], ["i", ".", "l", "be", "right", "back"], ["i", ".", "e", "seen", "it"], ["that", "'s", "why", "i", "'m", "here"], ["where", "are", "we", "going", "?"], ["i", "don", "'t", "think", "so"], ["i", "'m", "afraid", "i", "can", "'t"], ["what", "do", "you", "think", "?"]], "scores": [-6.194799184799194, -10.204551219940186, -6.687476634979248, -9.613704562187195, -10.226739525794983, -10.378439754247665, -8.190899968147278, -8.144536197185516, -11.765941381454468, -7.818684697151184]}, {"input": ["make", "a", "right", ".", "you", "can", "'t", "miss", "it", "."], "pred": [["i", "can", "'t", "believe", "it"], ["what", "do", "you", "mean", "?"], ["i", ".", "l", "show", "you"], ["i", "don", "'t", "think", "so"], ["that", "'s", "the", "way", "it", "is"], ["i", ".", "l", "be", "right", "back"], ["i", ".", "l", "take", "care", "of", "it"], ["i", ".", "e", "got", "to", "go"], ["i", ".", "e", "never", "seen", "anything", "like", "it"], ["you", "don", "'t", "have", "to", "do", "that"]], "scores": [-8.942341208457947, -7.519494414329529, -9.233319878578186, -8.247636616230011, -9.703946232795715, -8.462908387184143, -9.4635429084301, -9.944419384002686, -10.950791239738464, -11.2318976521492]}, {"input": ["do", "you", "think", "they", "'ll", "walk", "away", "?"], "pred": [["what", "do", "you", "think", "of", "that", "?"], ["i", "don", "'t", "think", "so"], ["i", "?", "e", "seen", "them"], ["what", "are", "you", "doing", "?"], ["they", "'r", "e", "all", "dead"], ["what", "do", "you", "mean", "?"], ["what", "are", "you", "going", "to", "do", "?"], ["i", "?", "l", "be", "right", "back"], ["what", "'s", "the", "matter", "?"], ["that", "'s", "what", "they", "say"]], "scores": [-8.975654482841492, -7.4242448806762695, -9.999335646629333, -6.606370449066162, -9.456762671470642, -6.0877732038497925, -9.320997953414917, -9.444383025169373, -7.346698462963104, -9.841682255268097]}, {"input": ["you", "sure", "know", "how", "to", "take", "a", "lot", "of", "punishment", "."], "pred": [["what", "do", "you", "mean", "?"], ["i", ".", "l", "be", "right", "back"], ["i", "know", "what", "you", "'r", "e", "thinking"], ["i", ".", "l", "tell", "you", "what"], ["i", ".", "e", "been", "thinking"], ["i", "don", "'t", "know", "what", "to", "say"], ["i", "don", "'t", "think", "so"], ["you", "know", "what", "i", "mean", "?"], ["i", "don", "'t", "want", "to"], ["don", "'t", "worry", "about", "it"]], "scores": [-6.9284074902534485, -8.766308784484863, -9.512258678674698, -8.560809850692749, -9.655984044075012, -9.42623782157898, -7.982550024986267, -8.95056939125061, -10.707823276519775, -8.567037343978882]}, {"input": ["bring", "down", "the", "money", "or", "your", "friend", "'s", "dead", "!"], "pred": [["get", "out", "of", "here", "!"], ["what", "are", "you", "doing", "?"], ["what", "do", "you", "want", "?"], ["i", "!", "l", "kill", "you", "!"], ["i", "don", "'t", "know", "!"], ["get", "out", "of", "the", "way", "!"], ["i", "don", "'t", "care", "!"], ["what", "'s", "the", "matter", "?"], ["you", "'r", "e", "out", "of", "your", "mind", "!"], ["come", "on", "let", "'s", "go", "!"]], "scores": [-5.249262273311615, -5.453180909156799, -5.861233592033386, -7.475068777799606, -8.614694237709045, -6.672547399997711, -8.402903079986572, -6.173263967037201, -10.382554054260254, -7.954048961400986]}, {"input": ["why", "the", "hell", "are", "we", "wasting", "time", "here", "?", "!"], "pred": [["what", "are", "you", "talking", "about", "?"], ["what", "are", "you", "doing", "?"], ["what", "the", "hell", "is", "this", "?"], ["i", "don", "'t", "think", "so"], ["i", "don", "'t", "know", "!"], ["i", "!", "l", "be", "right", "back"], ["i", "don", "'t", "know", "what", "to", "say"], ["what", "'s", "the", "matter", "?"], ["that", "'s", "why", "i", "'m", "here"], ["get", "out", "of", "here", "!"]], "scores": [-6.364373207092285, -6.212709903717041, -8.146377205848694, -7.599665582180023, -7.675386428833008, -8.790023446083069, -9.789492130279541, -6.74717378616333, -9.949185729026794, -7.608783781528473]}, {"input": ["i", "'m", "really", "not", "that", "hungry", "."], "pred": [["i", "'m", "not", "so", "sure"], ["what", "are", "you", "doing", "?"], ["what", "do", "you", "think", "you", "'r", "e", "doing", "?"], ["i", "don", "'t", "think", "so"], ["i", ".", "l", "be", "right", "back"], ["i", ".", "e", "got", "to", "go"], ["no", "i", "'m", "not", "hungry"], ["i", ".", "l", "tell", "you", "what"], ["don", "'t", "worry", "about", "it"], ["you", "know", "what", "i", "mean", "?"]], "scores": [-9.184001207351685, -5.968758225440979, -9.402584075927734, -7.6440393924713135, -8.49867045879364, -10.200156331062317, -9.290196180343628, -8.894431471824646, -8.233287572860718, -8.923646688461304]}, {"input": ["what", "are", "you", "looking", "to", "read", "?"], "pred": [["what", "are", "you", "doing", "?"], ["what", "do", "you", "mean", "?"], ["i", "don", "'t", "know", "what", "to", "say"], ["i", "?", "l", "be", "right", "back"], ["i", "don", "'t", "think", "so"], ["what", "do", "you", "think", "you", "'r", "e", "doing", "?"], ["what", "'s", "the", "matter", "?"], ["it", "'s", "been", "a", "long", "time"], ["i", "can", "'t", "believe", "it"], ["let", "'s", "get", "out", "of", "here"]], "scores": [-5.752268314361572, -6.543619155883789, -9.104294061660767, -8.200639009475708, -7.6861714124679565, -9.695557296276093, -6.347084164619446, -9.807063221931458, -8.445217728614807, -9.044991463422775]}, {"input": ["too", "many", "people", "know", "about", "my", "involvement", "in", "this", "."], "pred": [["i", "don", "'t", "think", "so"], ["i", "don", "'t", "know", "what", "to", "say"], ["let", "me", "tell", "you", "something"], ["i", "don", "'t", "want", "to", "talk", "about", "it"], ["what", "do", "you", "mean", "?"], ["it", "'s", "been", "a", "long", "time"], ["that", "'s", "why", "i", "'m", "here"], ["i", "'m", "glad", "you", "'r", "e", "here"], ["i", ".", "e", "been", "thinking"], ["i", "can", "'t", "believe", "it"]], "scores": [-7.752888381481171, -8.816085994243622, -8.523426204919815, -10.527199655771255, -7.01227068901062, -10.039146065711975, -9.245995253324509, -9.760912775993347, -9.624696612358093, -8.250802159309387]}, {"input": ["i", "told", "you", "the", "facts", "!", "he", "abandoned", "us", "--", "those", "are", "the", "facts", "."], "pred": [["let", "me", "tell", "you", "something"], ["i", "don", "'t", "know", "what", "to", "say"], ["what", "do", "you", "mean", "?"], ["i", "didn", "'t", "say", "that"], ["i", "think", "you", "'r", "e", "right"], ["i", "don", "'t", "believe", "it"], ["that", "'s", "what", "he", "said"], ["what", "does", "that", "mean", "?"], ["i", "don", "'t", "think", "so"], ["what", "are", "you", "doing", "?"]], "scores": [-8.300582259893417, -9.926041603088379, -6.184882402420044, -8.773627191781998, -10.173198878765106, -7.823496580123901, -9.999547868967056, -7.871737837791443, -7.557694792747498, -7.9022544622421265]}, {"input": ["you", "really", "got", "a", "masters", "degree", "?"], "pred": [["you", "know", "what", "i", "mean"], ["you", "'r", "e", "a", "?"], ["i", "?", "e", "got", "to", "go"], ["what", "do", "you", "mean", "?"], ["i", "don", "'t", "think", "so"], ["i", "'m", "not", "a", "?"], ["let", "me", "tell", "you", "something"], ["what", "are", "you", "talking", "about", "?"], ["i", "don", "'t", "want", "to"], ["i", "don", "'t", "get", "it"]], "scores": [-9.252863883972168, -8.356835722923279, -10.664511024951935, -6.031009197235107, -7.89421546459198, -9.436435341835022, -8.106176644563675, -6.766023874282837, -10.977994322776794, -8.292358830571175]}, {"input": ["he", "said", "we", "'re", "all", "going", "to", "have", "to", "go", "talk", "to", "the", "guy", "."], "pred": [["what", "did", "he", "say", "?"], ["he", "said", "he", "didn", "'t", "know"], ["i", "can", "'t", "believe", "it"], ["what", "'s", "going", "on", "?"], ["i", "don", "'t", "think", "so"], ["he", "said", "he", "wanted", "to", "talk", "to", "you"], ["he", "didn", "'t", "say", "anything"], ["i", "don", "'t", "know", "what", "to", "say"], ["why", "didn", "'t", "you", "tell", "me", "?"], ["that", "'s", "what", "he", "said"]], "scores": [-4.328252196311951, -11.22489333152771, -8.937761187553406, -6.9947497844696045, -8.296083569526672, -10.132542848587036, -8.523579120635986, -9.765092968940735, -8.899803400039673, -7.826106786727905]}], "score": -1.5360296892661593, "ppl": 4.64610711438351}